MANIFEST.in
setup.py
RESOURCES/.suffix
RESOURCES/BENCH/dir/install.sh
RESOURCES/BENCH/fdisk/set.sh
RESOURCES/BENCH/gcc/install.sh
RESOURCES/BENCH/git/install.sh
RESOURCES/BENCH/git/set.sh
RESOURCES/BENCH/js/install.sh
RESOURCES/BENCH/py3/install.cmd
RESOURCES/BENCH/py3/install.sh
RESOURCES/BENCH/rpm/install.sh
RESOURCES/BENCH/set_root/set.cmd
RESOURCES/BENCH/terminal/set.sh
RESOURCES/BENCH/vim/install.sh
ecli/__init__.py
ecli/abbr.py
ecli/cmmn.py
ecli.egg-info/PKG-INFO
ecli.egg-info/SOURCES.txt
ecli.egg-info/dependency_links.txt
ecli.egg-info/entry_points.txt
ecli.egg-info/top_level.txt
ecli/bin/__init__.py
ecli/bin/abbr.py
ecli/bin/htmlq.py
ecli/bin/jsonq.py
ecli/bin/lcp.py
ecli/bin/lcut.py
ecli/bin/ldd.py
ecli/bin/pobj.py
ecli/bin/srch.py